[
    {
        "id": "respond-starter",
        "name": "Respond Starter",
        "url": "product\/respond-starter",
        "description": "Respond Starter Subscription",
        "shipped": false,
        "price": 100,
        "file": "",
        "subscription": "true",
        "plan": "respond-starter",
        "planPrice": "$100 \/month",
        "images": [],
        "options": []
    },
    {
        "id": "respond-core",
        "name": "Respond Core",
        "url": "product\/respond-core",
        "description": "Respond Core Subscription",
        "shipped": false,
        "price": 250,
        "file": "",
        "subscription": "true",
        "plan": "respond-core",
        "planPrice": "$250 \/month",
        "images": [],
        "options": []
    },
    {
        "id": "respond-pro",
        "name": "Respond Pro",
        "url": "product\/respond-pro",
        "description": "Respond Pro Subscription",
        "shipped": false,
        "price": 500,
        "file": "",
        "subscription": "true",
        "plan": "respond-pro",
        "planPrice": "$500 \/month",
        "images": [],
        "options": []
    }
]